pyqaxe/__init__.py
pyqaxe/cache.py
pyqaxe/util.py
pyqaxe/version.py
pyqaxe/mines/__init__.py
pyqaxe/mines/directory.py
pyqaxe/mines/glotzformats.py
pyqaxe/mines/gtar.py
pyqaxe/mines/tarfile.py
pyqaxe-0.1.2.dist-info/METADATA
pyqaxe-0.1.2.dist-info/RECORD
pyqaxe-0.1.2.dist-info/WHEEL
pyqaxe-0.1.2.dist-info/top_level.txt
